NekoRMD/Control.py
NekoRMD/MotorInterface.py
NekoRMD/MotorLogs.py
NekoRMD/MotorType.py
NekoRMD/NekoRMD.py
NekoRMD/Telemetry.py
NekoRMD/__init__.py
NekoRMD/ican.py
NekoRMD-0.2.2.dist-info/METADATA
NekoRMD-0.2.2.dist-info/WHEEL
NekoRMD-0.2.2.dist-info/top_level.txt
NekoRMD-0.2.2.dist-info/RECORD
