Metadata-Version: 2.1
Name: NekoRMD
Version: 0.2.2
Summary: NekoRMD is a Python library for controlling RMD series motors through a CAN interface. It provides a wide range of functions for motor control and monitoring.
Home-page: https://github.com/NekoRMD/NekoRMD
Author: Artem-Darius Weber
Author-email: neko-rmd@k-lab.su
Classifier: Programming Language :: Python :: 3
Classifier: License :: OSI Approved :: MIT License
Classifier: Operating System :: OS Independent
Requires-Python: >=3.6
Requires-Dist: python-can
